deansi.py
deansi-1.2.1.dist-info/LICENSE
deansi-1.2.1.dist-info/METADATA
deansi-1.2.1.dist-info/WHEEL
deansi-1.2.1.dist-info/entry_points.txt
deansi-1.2.1.dist-info/top_level.txt
deansi-1.2.1.dist-info/RECORD
