Metadata-Version: 2.1
Name: deansi
Version: 1.2.1
Summary: ANSI codes to HTML converter
Home-page: https://github.com/GuifiBaix/python-deansi
Author: David García Garzón
Author-email: voki@canvoki.net
License: GNU Affero General Public License v3 or later (AGPLv3+)
Classifier: Programming Language :: Python
Classifier: Programming Language :: Python :: 2
Classifier: Programming Language :: Python :: 3
Classifier: Topic :: Software Development :: Libraries :: Python Modules
Classifier: Topic :: System :: Logging
Classifier: Topic :: Text Processing :: Filters
Classifier: Topic :: Text Processing :: Markup :: HTML
Classifier: Environment :: Console
Classifier: Intended Audience :: Developers
Classifier: Development Status :: 5 - Production/Stable
Classifier: License :: OSI Approved :: GNU Affero General Public License v3 or later (AGPLv3+)
Classifier: Operating System :: OS Independent
License-File: LICENSE
